{
  "_fv": 24,
  "_type": "livingentity",
  "definition": {
    "mobName": "Hertx",
    "mobLabel": "§6[Idle]",
    "mobModelName": "Modelhertx_model_wait_s1",
    "mobModelTexture": "hertx_variant_soldier_texture.png",
    "mobModelGlowTexture": "hertx_variant_soldier_glow.png",
    "modelWidth": 0.7,
    "modelHeight": 2.0,
    "modelShadowSize": 0.6,
    "mountedYOffset": 0.0,
    "hasSpawnEgg": false,
    "spawnEggBaseColor": {
      "value": -13421773,
      "falpha": 0.0
    },
    "spawnEggDotColor": {
      "value": -154,
      "falpha": 0.0
    },
    "creativeTab": {
      "value": "No creative tab entry"
    },
    "isBoss": false,
    "bossBarColor": "PINK",
    "bossBarType": "PROGRESS",
    "equipmentMainHand": {
      "value": ""
    },
    "equipmentOffHand": {
      "value": ""
    },
    "equipmentHelmet": {
      "value": ""
    },
    "equipmentBody": {
      "value": ""
    },
    "equipmentLeggings": {
      "value": ""
    },
    "equipmentBoots": {
      "value": ""
    },
    "mobBehaviourType": "Creature",
    "mobCreatureType": "UNDEFINED",
    "attackStrength": 5,
    "attackKnockback": 0.2,
    "knockbackResistance": 0.4,
    "movementSpeed": 0.3,
    "armorBaseValue": 7.5,
    "trackingRange": 128,
    "health": 40,
    "xpAmount": 16,
    "waterMob": false,
    "flyingMob": false,
    "guiBoundTo": "<NONE>",
    "inventorySize": 9,
    "inventoryStackSize": 64,
    "disableCollisions": false,
    "ridable": false,
    "canControlForward": false,
    "canControlStrafe": false,
    "immuneToFire": false,
    "immuneToArrows": false,
    "immuneToFallDamage": true,
    "immuneToCactus": true,
    "immuneToDrowning": true,
    "immuneToLightning": false,
    "immuneToPotions": false,
    "immuneToPlayer": false,
    "immuneToExplosion": false,
    "immuneToTrident": false,
    "immuneToAnvil": false,
    "immuneToWither": false,
    "immuneToDragonBreath": false,
    "mobDrop": {
      "value": ""
    },
    "livingSound": {
      "value": "CUSTOM:robot_beep"
    },
    "hurtSound": {
      "value": "entity.slime.hurt"
    },
    "deathSound": {
      "value": "CUSTOM:death_beep"
    },
    "stepSound": {
      "value": "entity.slime.squish"
    },
    "spawnParticles": false,
    "particleToSpawn": {
      "value": "EXPLOSION_NORMAL"
    },
    "particleSpawningShape": "Spread",
    "particleSpawningRadious": 0.5,
    "particleAmount": 4,
    "whenMobDies": {
      "name": "HertxEntityDies"
    },
    "whenMobIsHurt": {
      "name": "HertxSolWaitEntityIsHurt"
    },
    "onRightClickedOn": {
      "name": "HertxSolWaitRightClickedOnEntity"
    },
    "whenThisMobKillsAnother": {
      "name": "HertxThisEntityKillsAnotherOne"
    },
    "onPlayerCollidesWith": {
      "name": "HertxPlayerCollidesWithThisEntity"
    },
    "onInitialSpawn": {
      "name": "HertxOnInitialEntitySpawn"
    },
    "hasAI": true,
    "aiBase": "(none)",
    "aixml": "<xml xmlns=\"https://developers.google.com/blockly/xml\"><block type=\"aitasks_container\" deletable=\"false\" x=\"40\" y=\"40\"><next><block type=\"watch_closest_entity\"><field name=\"radius\">6</field><field name=\"entity\">EntityPlayer</field><field name=\"condition\">null,null</field><next><block type=\"look_around\"><field name=\"condition\">null,null</field><next><block type=\"swim_in_water\"><field name=\"condition\">null,null</field></block></next></block></next></block></next></block></xml>",
    "breedable": true,
    "tameable": true,
    "breedTriggerItems": [
      {
        "value": "CUSTOM:Darklatexgoo"
      },
      {
        "value": "Items.IRON_NUGGET"
      },
      {
        "value": "Items.IRON_INGOT"
      }
    ],
    "ranged": false,
    "rangedAttackItem": {
      "value": ""
    },
    "rangedItemType": "Default item",
    "spawnThisMob": false,
    "doesDespawnWhenIdle": false,
    "spawningProbability": 20,
    "mobSpawningType": "monster",
    "minNumberOfMobsPerGroup": 4,
    "maxNumberOfMobsPerGroup": 4,
    "restrictionBiomes": [],
    "spawnInDungeons": false
  }
}