{
  "group": "latex",
  "type": "minecraft:crafting_shaped",
  "pattern": [
    "012",
    "345",
    "678"
  ],
  "key": {
    "0": {
      "item": "minecraft:blue_concrete"
    },
    "1": {
      "item": "minecraft:white_concrete"
    },
    "2": {
      "item": "minecraft:blue_concrete"
    },
    "3": {
      "item": "minecraft:white_concrete"
    },
    "4": {
      "item": "minecraft:white_concrete"
    },
    "5": {
      "item": "minecraft:white_concrete"
    },
    "6": {
      "item": "minecraft:blue_concrete"
    },
    "7": {
      "item": "minecraft:blue_concrete"
    },
    "8": {
      "item": "minecraft:blue_concrete"
    }
  },
  "result": {
    "item": "latex:bluelabblock_2",
    "count": 9
  }
}